steam_editor_tools/__init__.py
steam_editor_tools/utils.py
steam_editor_tools/version.py
steam_editor_tools/bbcode/__init__.py
steam_editor_tools/bbcode/guide.py
steam_editor_tools/bbcode/nodes.py
steam_editor_tools/bbcode/parser.py
steam_editor_tools/bbcode/renderer.py
steam_editor_tools/bbcode/plugins/__init__.py
steam_editor_tools/bbcode/plugins/alert.py
steam_editor_tools/bbcode/plugins/mark.py
steam_editor_tools/improc/__init__.py
steam_editor_tools/improc/composer.py
steam_editor_tools/improc/data.py
steam_editor_tools/improc/effects.py
steam_editor_tools/improc/font.py
steam_editor_tools/improc/latex_to_img.py
steam_editor_tools/improc/layer.py
steam_editor_tools/improc/overlays.py
steam_editor_tools/improc/renderer.py
steam_editor_tools/improc/tools.py
steam_editor_tools/improc/variables.py
steam_editor_tools/steaminfo/__init__.py
steam_editor_tools/steaminfo/data.py
steam_editor_tools/steaminfo/query.py
steam_editor_tools/steaminfo/utils.py
steam_editor_tools-0.4.1.dist-info/licenses/LICENSE
steam_editor_tools-0.4.1.dist-info/METADATA
steam_editor_tools-0.4.1.dist-info/WHEEL
steam_editor_tools-0.4.1.dist-info/top_level.txt
steam_editor_tools-0.4.1.dist-info/zip-safe
steam_editor_tools-0.4.1.dist-info/RECORD
