Metadata-Version: 2.4
Name: steam-editor-tools
Version: 0.4.1
Summary: This package offers editor tools helping users write Steam guides and reviews. Support Steam information queries, image editing tools, and BBCode text processing tools.
Author-email: Yuchen Jin <cainmagi@gmail.com>
Maintainer-email: Yuchen Jin <cainmagi@gmail.com>
License: MIT License
Project-URL: Homepage, https://github.com/cainmagi/steam-editor-tools
Project-URL: Documentation, https://cainmagi.github.io/steam-editor-tools/
Project-URL: Repository, https://github.com/cainmagi/steam-editor-tools.git
Project-URL: Issues, https://github.com/cainmagi/steam-editor-tools/issues
Project-URL: Changelog, https://github.com/cainmagi/steam-editor-tools/blob/main/Changelog.md
Keywords: python,python3,python-library,image-processing,steam-api,steam-guide,steam-bbcode,steam-bbcode-converter,bbcode,markdown-to-bbcode,html-to-bbcode
Classifier: Development Status :: 3 - Alpha
Classifier: Environment :: Console
Classifier: Intended Audience :: Developers
Classifier: Programming Language :: Python :: 3
Classifier: Programming Language :: Python :: 3 :: Only
Classifier: Programming Language :: Python :: 3.10
Classifier: Programming Language :: Python :: 3.11
Classifier: Programming Language :: Python :: 3.12
Classifier: Programming Language :: Python :: 3.13
Classifier: Programming Language :: Python :: 3.14
Classifier: License :: OSI Approved :: MIT License
Classifier: Operating System :: OS Independent
Classifier: Framework :: Pydantic
Classifier: Framework :: Pydantic :: 2
Classifier: Topic :: Text Processing :: Markup
Classifier: Topic :: Text Processing :: Markup :: HTML
Classifier: Topic :: Text Processing :: Markup :: Markdown
Requires-Python: >=3.10
License-File: LICENSE
Requires-Dist: typing-extensions>=4.1.0
Requires-Dist: pydantic>=2
Requires-Dist: markdown-it-py[linkify]
Requires-Dist: beautifulsoup4
Requires-Dist: pillow>=10.0.0
Requires-Dist: fonttools>=4.0.0
Requires-Dist: httpx
Requires-Dist: rapidfuzz
Provides-Extra: dev
Requires-Dist: typing-extensions>=4.1.0; extra == "dev"
Requires-Dist: black; extra == "dev"
Requires-Dist: flake8; extra == "dev"
Requires-Dist: flake8-black; extra == "dev"
Requires-Dist: build; extra == "dev"
Requires-Dist: wheel; extra == "dev"
Provides-Extra: test
Requires-Dist: pytest; extra == "test"
Requires-Dist: pytest-base-url; extra == "test"
Requires-Dist: pytest-html; extra == "test"
Requires-Dist: pytest-metadata; extra == "test"
Requires-Dist: py; extra == "test"
Requires-Dist: pytest-variables; extra == "test"
Requires-Dist: pytest-xdist; extra == "test"
Requires-Dist: numpy; extra == "test"
Requires-Dist: scikit-image; extra == "test"
Dynamic: license-file
